{
    "maintainer": "Opscode, Inc.",
    "replacing": {
    },
    "description": "Installs C compiler / build tools",
    "maintainer_email": "cookbooks@opscode.com",
    "groupings": {
    },
    "attributes": {
    },
    "platforms": {
      "debian": [

      ],
      "centos": [

      ],
      "ubuntu": [

      ]
    },
    "recommendations": {
    },
    "dependencies": {
    },
    "version": "0.7.0",
    "suggestions": {
    },
    "conflicting": {
    },
    "license": "Apache 2.0",
    "name": "build-essential",
    "long_description": "",
    "recipes": {
    },
    "providing": {
    }
  }